x448/__init__.py
x448/x448.py
x448_python-1.0.0.dist-info/LICENSE
x448_python-1.0.0.dist-info/METADATA
x448_python-1.0.0.dist-info/WHEEL
x448_python-1.0.0.dist-info/top_level.txt
x448_python-1.0.0.dist-info/RECORD
