Metadata-Version: 2.1
Name: x448-python
Version: 1.0.0
Summary: Pure Python3 implementation of x448.
Home-page: https://github.com/plizonczyk/x448-python
Author: Piotr Lizonczyk
Author-email: plizonczyk.public@gmail.com
License: UNKNOWN
Platform: UNKNOWN
Classifier: Programming Language :: Python :: 3
Classifier: License :: OSI Approved :: MIT License
Classifier: Operating System :: OS Independent
